yaml_package/__init__.py
yaml_package/bunch.py
yaml_package/yaml_package_loader.py
yaml_package-0.1.dist-info/LICENSE
yaml_package-0.1.dist-info/METADATA
yaml_package-0.1.dist-info/WHEEL
yaml_package-0.1.dist-info/top_level.txt
yaml_package-0.1.dist-info/RECORD
