Metadata-Version: 2.1
Name: yaml-package
Version: 0.1
License-File: LICENSE
Requires-Dist: pandas
Requires-Dist: rich
Requires-Dist: beartype
Requires-Dist: pyyaml
